{"elapsed":"0.507","endpoint-url":"https://github.com/digital-land/planning-permission-type-collection/raw/main/data/planning-permission-type.csv","entry-date":"2023-03-12T00:19:03.788850","request-headers":{"Accept":"*/*","Accept-Encoding":"gzip, deflate","Connection":"keep-alive","User-Agent":"DLUHC Digital Land"},"resource":"deb2fc4b3a5a1838f955591aaadfe1f2005a54909cfcffbe28523ade2b4fd3f2","response-headers":{"Accept-Ranges":"bytes","Access-Control-Allow-Origin":"*","Cache-Control":"max-age=300","Connection":"keep-alive","Content-Encoding":"gzip","Content-Length":"250","Content-Security-Policy":"default-src 'none'; style-src 'unsafe-inline'; sandbox","Content-Type":"text/plain; charset=utf-8","Date":"Sun, 12 Mar 2023 00:19:04 GMT","ETag":"W/\"c6e01e0e94ff6f62e0d319b6dc4f983157d56fc1f8a129f43c8d4681d8fd4531\"","Expires":"Sun, 12 Mar 2023 00:24:04 GMT","Source-Age":"0","Strict-Transport-Security":"max-age=31536000","Vary":"Authorization,Accept-Encoding,Origin","Via":"1.1 varnish","X-Cache":"MISS","X-Cache-Hits":"0","X-Content-Type-Options":"nosniff","X-Fastly-Request-ID":"a6eaff6519db1fa44cffe4776ac786a5ed905b22","X-Frame-Options":"deny","X-GitHub-Request-Id":"976A:308B:523F98:7E09EF:640D1A78","X-Served-By":"cache-iad-kiad7000110-IAD","X-Timer":"S1678580344.479854,VS0,VE71","X-XSS-Protection":"1; mode=block"},"ssl-verify":true,"status":"200"}