{"elapsed":"0.332","endpoint-url":"https://github.com/digital-land/planning-permission-type-collection/raw/main/data/planning-permission-type.csv","entry-date":"2021-04-15T00:17:14.948600","request-headers":{"Accept":"*/*","Accept-Encoding":"gzip, deflate","Connection":"keep-alive","User-Agent":"Digital Land"},"resource":"deb2fc4b3a5a1838f955591aaadfe1f2005a54909cfcffbe28523ade2b4fd3f2","response-headers":{"Accept-Ranges":"bytes","Access-Control-Allow-Origin":"*","Cache-Control":"max-age=300","Connection":"keep-alive","Content-Encoding":"gzip","Content-Length":"250","Content-Security-Policy":"default-src 'none'; style-src 'unsafe-inline'; sandbox","Content-Type":"text/plain; charset=utf-8","Date":"Thu, 15 Apr 2021 00:17:15 GMT","ETag":"W/\"c6e01e0e94ff6f62e0d319b6dc4f983157d56fc1f8a129f43c8d4681d8fd4531\"","Expires":"Thu, 15 Apr 2021 00:22:15 GMT","Source-Age":"0","Strict-Transport-Security":"max-age=31536000","Vary":"Authorization,Accept-Encoding","Via":"1.1 varnish","X-Cache":"MISS","X-Cache-Hits":"0","X-Content-Type-Options":"nosniff","X-Fastly-Request-ID":"32695086dabb519b938f204de145b1ecb65cf01a","X-Frame-Options":"deny","X-GitHub-Request-Id":"D608:81F8:728A9:8C370:6077860B","X-Served-By":"cache-sea4482-SEA","X-Timer":"S1618445836.682101,VS0,VE142","X-XSS-Protection":"1; mode=block"},"ssl-verify":true,"status":"200"}